{
  "LstReportObjectOnRow": [
    {
      "ReportObjectId": "056f28b5-7709-4b9d-aa8f-fe83eaecc674",
      "ReportObjectName": "Level 1 Category",
      "ObjectGroupName": "Classification",
      "DisplayName": "Level 1 Category",
      "LayoutArea": 0,
      "SequenceNumber": 16,
      "IsFilterable": true,
      "IsDerived": false,
      "IsTransactional": false,
      "IsSelectAll": true,
      "ReportObjectType": 1,
      "ReportObjectDataType": 0,
      "IsDrillToTransactional": true,
      "DrillTransactionOrder": 24,
      "FilterTypeObjectId": "10efc3f0-7ec5-4d8f-b6da-0b476d07629d",
      "FilterType": 1,
      "FormatKey": "",
      "ReportObjectWidth": 150,
      "IsDrill": false,
      "CustomFormula": null,
      "WijmoGridAggregatedType": 0
    }
  ],
  "LstReportObjectOnColumn": [
    {
      "ReportObjectId": "836b0b8c-922f-4f05-bf4c-40b45f7051a7",
      "ReportObjectName": "Region",
      "ObjectGroupName": "Location",
      "DisplayName": "Region",
      "LayoutArea": 1,
      "SequenceNumber": 35,
      "IsFilterable": true,
      "IsDerived": false,
      "IsTransactional": false,
      "IsSelectAll": true,
      "ReportObjectType": 1,
      "ReportObjectDataType": 0,
      "IsDrillToTransactional": true,
      "DrillTransactionOrder": 16,
      "FilterTypeObjectId": "10efc3f0-7ec5-4d8f-b6da-0b476d07629d",
      "FilterType": 1,
      "FormatKey": "",
      "ReportObjectWidth": 150,
      "IsDrill": false,
      "CustomFormula": null,
      "WijmoGridAggregatedType": 0
    }
  ],
  "LstReportObjectOnValue": [
    {
      "ReportObjectId": "0c6af54e-e70b-40c2-88e0-8d7dfc263433",
      "ReportObjectName": "Spend USD",
      "ObjectGroupName": "Measure",
      "DisplayName": "Spend USD",
      "LayoutArea": 2,
      "SequenceNumber": 1,
      "IsFilterable": true,
      "IsDerived": false,
      "IsTransactional": false,
      "IsSelectAll": false,
      "ReportObjectType": 0,
      "ReportObjectDataType": 5,
      "IsDrillToTransactional": true,
      "DrillTransactionOrder": 84,
      "FilterTypeObjectId": "9ef922e5-ff0b-408f-b8a3-a6c5928d5d29",
      "FilterType": 2,
      "FormatKey": "USD",
      "ReportObjectWidth": 150,
      "IsDrill": false,
      "CustomFormula": null,
      "WijmoGridAggregatedType": 0
    }
  ],
  "LstReportSortingDetails": [
    {
      "ReportObject": {
        "ReportObjectId": "836b0b8c-922f-4f05-bf4c-40b45f7051a7",
        "ReportObjectName": "Region",
        "ObjectGroupName": "Location",
        "DisplayName": "Region",
        "LayoutArea": 0,
        "SequenceNumber": 35,
        "IsFilterable": true,
        "IsDerived": false,
        "IsTransactional": false,
        "IsSelectAll": true,
        "ReportObjectType": 1,
        "ReportObjectDataType": 0,
        "IsDrillToTransactional": true,
        "DrillTransactionOrder": 16,
        "FilterTypeObjectId": "10efc3f0-7ec5-4d8f-b6da-0b476d07629d",
        "FilterType": 0,
        "FormatKey": "",
        "ReportObjectWidth": null,
        "IsDrill": false,
        "CustomFormula": null,
        "WijmoGridAggregatedType": 0
      },
      "SortOrder": 1,
      "SortType": 0
    },
    {
      "ReportObject": {
        "ReportObjectId": "056f28b5-7709-4b9d-aa8f-fe83eaecc674",
        "ReportObjectName": "Level 1 Category",
        "ObjectGroupName": "Classification",
        "DisplayName": "Level 1 Category",
        "LayoutArea": 0,
        "SequenceNumber": 16,
        "IsFilterable": true,
        "IsDerived": false,
        "IsTransactional": false,
        "IsSelectAll": true,
        "ReportObjectType": 1,
        "ReportObjectDataType": 0,
        "IsDrillToTransactional": true,
        "DrillTransactionOrder": 24,
        "FilterTypeObjectId": "10efc3f0-7ec5-4d8f-b6da-0b476d07629d",
        "FilterType": 0,
        "FormatKey": "",
        "ReportObjectWidth": null,
        "IsDrill": false,
        "CustomFormula": null,
        "WijmoGridAggregatedType": 0
      },
      "SortOrder": 2,
      "SortType": 0
    },
    {
      "ReportObject": {
        "ReportObjectId": "0c6af54e-e70b-40c2-88e0-8d7dfc263433",
        "ReportObjectName": "Spend USD",
        "ObjectGroupName": "Measure",
        "DisplayName": "Spend USD",
        "LayoutArea": 0,
        "SequenceNumber": 1,
        "IsFilterable": true,
        "IsDerived": false,
        "IsTransactional": false,
        "IsSelectAll": false,
        "ReportObjectType": 0,
        "ReportObjectDataType": 5,
        "IsDrillToTransactional": true,
        "DrillTransactionOrder": 84,
        "FilterTypeObjectId": "9ef922e5-ff0b-408f-b8a3-a6c5928d5d29",
        "FilterType": 0,
        "FormatKey": "USD",
        "ReportObjectWidth": null,
        "IsDrill": false,
        "CustomFormula": null,
        "WijmoGridAggregatedType": 0
      },
      "SortOrder": 3,
      "SortType": 1
    }
  ],
  "lstFilterReportObject": [
    {
      "ReportObject": {
        "ReportObjectId": "0c6af54e-e70b-40c2-88e0-8d7dfc263433",
        "ReportObjectName": "Spend USD",
        "ObjectGroupName": "Measure",
        "DisplayName": "Spend USD",
        "LayoutArea": 0,
        "SequenceNumber": 1,
        "IsFilterable": true,
        "IsDerived": false,
        "IsTransactional": false,
        "IsSelectAll": false,
        "ReportObjectType": 0,
        "ReportObjectDataType": 5,
        "IsDrillToTransactional": true,
        "DrillTransactionOrder": 84,
        "FilterTypeObjectId": "9ef922e5-ff0b-408f-b8a3-a6c5928d5d29",
        "FilterType": 2,
        "FormatKey": null,
        "ReportObjectWidth": null,
        "IsDrill": false,
        "CustomFormula": null,
        "WijmoGridAggregatedType": 0
      },
      "FilterCondition": {
        "FilterConditionObjectId": "f24011fe-f339-42a1-8a60-c980e3dc9941",
        "Name": "Less than",
        "Condition": 13,
        "Formulla": null,
        "IsPeriodFilter": false,
        "FilterTypeObjectId": "00000000-0000-0000-0000-000000000000",
        "FilterType": 0
      },
      "FilterValue": "[\"100000000\"]",
      "FilterBy": 2,
      "IsSliderWidgetFilter": false
    }
  ],
  "ReportId": 299,
  "ReportDetailObjectId": null,
  "ReportName": "test_report_ignore",
  "DisplayName": "test_report_ignore",
  "ReportDescription": "",
  "ReportType": 0,
  "IsStandardReport": false,
  "DataSourceObjectId": "a9bf1050-6c9e-483f-9cac-92895b7db6fa",
  "CreatedBy": 44336704000050,
  "CreatedOn": "\/Date(1533669600000)\/",
  "ModifiedOn": "\/Date(1535394485673)\/",
  "ReportViewType": 0,
  "IsTotalRequired": true,
  "StakeholderCount": 0,
  "lstPinnedToViews": null,
  "ReportProperties": null
}